exportzlapi/__init__.py
exportzlapi/core.py
exportzlapi-1.0.1.dist-info/METADATA
exportzlapi-1.0.1.dist-info/WHEEL
exportzlapi-1.0.1.dist-info/top_level.txt
exportzlapi-1.0.1.dist-info/RECORD
