Metadata-Version: 2.1
Name: exportzlapi
Version: 1.0.1
Summary: Library ZaloAPI Pro
Home-page: 
Author: Lâm Minh Phú
Author-email: zalochatbot@gmail.com
Classifier: Programming Language :: Python :: 3
Classifier: License :: OSI Approved :: MIT License
Classifier: Operating System :: OS Independent
Requires-Dist: python-telegram-bot
Requires-Dist: requests
Requires-Dist: telebot
Requires-Dist: asyncio
